snorkelai/sdk/client/__init__.py
snorkelai/sdk/client/annotation_sources.py
snorkelai/sdk/client/connector_configs.py
snorkelai/sdk/client/ctx.py
snorkelai/sdk/client/external_models.py
snorkelai/sdk/client/files.py
snorkelai/sdk/client/fm_suite.py
snorkelai/sdk/client/secrets.py
snorkelai/sdk/client/synthetic.py
snorkelai/sdk/client/users.py
snorkelai/sdk/client/utils.py
snorkelai/sdk/client_v3/__init__.py
snorkelai/sdk/client_v3/annotation_sources.py
snorkelai/sdk/client_v3/connector_configs.py
snorkelai/sdk/client_v3/ctx.py
snorkelai/sdk/client_v3/external_models.py
snorkelai/sdk/client_v3/files.py
snorkelai/sdk/client_v3/fm_suite.py
snorkelai/sdk/client_v3/fm_type.py
snorkelai/sdk/client_v3/job_event.py
snorkelai/sdk/client_v3/secrets.py
snorkelai/sdk/client_v3/slices.py
snorkelai/sdk/client_v3/synthetic.py
snorkelai/sdk/client_v3/tdm/__init__.py
snorkelai/sdk/client_v3/tdm/api/__init__.py
snorkelai/sdk/client_v3/tdm/api/annotation.py
snorkelai/sdk/client_v3/tdm/api/annotation_tasks.py
snorkelai/sdk/client_v3/tdm/api/api_keys.py
snorkelai/sdk/client_v3/tdm/api/audit_logs.py
snorkelai/sdk/client_v3/tdm/api/backup.py
snorkelai/sdk/client_v3/tdm/api/benchmark.py
snorkelai/sdk/client_v3/tdm/api/cluster.py
snorkelai/sdk/client_v3/tdm/api/code.py
snorkelai/sdk/client_v3/tdm/api/connector_configs.py
snorkelai/sdk/client_v3/tdm/api/connectors.py
snorkelai/sdk/client_v3/tdm/api/cpu_profiling.py
snorkelai/sdk/client_v3/tdm/api/criteria.py
snorkelai/sdk/client_v3/tdm/api/criteria_templates.py
snorkelai/sdk/client_v3/tdm/api/data_connector.py
snorkelai/sdk/client_v3/tdm/api/data_connector_config.py
snorkelai/sdk/client_v3/tdm/api/data_connector_roles_router.py
snorkelai/sdk/client_v3/tdm/api/data_ingress_v2.py
snorkelai/sdk/client_v3/tdm/api/datapoint.py
snorkelai/sdk/client_v3/tdm/api/dataset_batch.py
snorkelai/sdk/client_v3/tdm/api/dataset_comments.py
snorkelai/sdk/client_v3/tdm/api/dataset_ground_truth.py
snorkelai/sdk/client_v3/tdm/api/dataset_tag_types.py
snorkelai_sdk-25.11.1.dist-info/WHEEL
snorkelai_sdk-25.11.1.dist-info/METADATA
snorkelai_sdk-25.11.1.dist-info/RECORD
